LICENSE.md
MANIFEST.in
README.md
example.png
setup.cfg
setup.py
dj_ajax_raw_id_fields/__init__.py
dj_ajax_raw_id_fields/admin.py
dj_ajax_raw_id_fields/urls.py
dj_ajax_raw_id_fields/views.py
dj_ajax_raw_id_fields/widgets.py
dj_ajax_raw_id_fields.egg-info/PKG-INFO
dj_ajax_raw_id_fields.egg-info/SOURCES.txt
dj_ajax_raw_id_fields.egg-info/dependency_links.txt
dj_ajax_raw_id_fields.egg-info/not-zip-safe
dj_ajax_raw_id_fields.egg-info/top_level.txt
dj_ajax_raw_id_fields/static/dj_ajax_raw_id_fields/js/dj_ajax_raw_id_fields.js
dj_ajax_raw_id_fields/templates/dj_ajax_raw_id_fields/label.html
dj_ajax_raw_id_fields/templates/dj_ajax_raw_id_fields/widgets/ajax_foreign_key_raw_id.html